chncal/__init__.py
chncal/bazi.py
chncal/festival.py
chncal/holiday.py
chncal/lunar.py
chncal/marry_match.py
chncal/solar_terms.py
chncal/trade_dates.py
chncal/utils.py
chncal/wuxing.py
chncal/xingzuo.py
chncal/constant_creator/__init__.py
chncal/constant_creator/chengming.py
chncal/constant_creator/hko_calendar.py
chncal/constant_creator/holiday.py
chncal/constant_creator/main.py
chncal/constant_creator/trade_dates.py
chncal/constants/__init__.py
chncal/constants/chengming.py
chncal/constants/hko_calendar.py
chncal/constants/holiday.py
chncal/constants/trade_dates.py
chncal-3.1.2025.dist-info/LICENSE
chncal-3.1.2025.dist-info/METADATA
chncal-3.1.2025.dist-info/WHEEL
chncal-3.1.2025.dist-info/top_level.txt
chncal-3.1.2025.dist-info/RECORD
