Metadata-Version: 2.1
Name: chncal
Version: 3.1.2025
Summary: Check if some day is holiday in china; Chinese lunar calendar.
Home-page: https://gitee.com/glhyy/ChnCal
Author: Genlovy Hoo
Author-email: genlovhyy@163.com
License: MIT License
License-File: LICENSE
Requires-Dist: dramkit
